README.md
setup.py
gnuplotpy/__init__.py
gnuplotpy/gnuplot.py
gnuplotpy.egg-info/PKG-INFO
gnuplotpy.egg-info/SOURCES.txt
gnuplotpy.egg-info/dependency_links.txt
gnuplotpy.egg-info/not-zip-safe
gnuplotpy.egg-info/top_level.txt