Metadata-Version: 1.0
Name: gnuplotpy
Version: 0.1
Summary: Basic Python interface to Gnuplot.
Home-page: https://github.com/jtambasco/gnuplotpy.git
Author: Jean-Luc Tambasco
Author-email: an.obscurity@gmail.com
License: MIT
Platform: UNKNOWN
